bitclone/__init__.py
bitclone/__main__.py
bitclone-0.30.dist-info/METADATA
bitclone-0.30.dist-info/RECORD
bitclone-0.30.dist-info/WHEEL
bitclone-0.30.dist-info/entry_points.txt
bitclone-0.30.dist-info/top_level.txt
