Metadata-Version: 2.1
Name: bitclone
Version: 0.30
Summary: Clone all your bitbucket repo
Home-page: http://github.com/rytsh/bitclone
Author: Eray Ates
Author-email: eates23@gmail.com
License: UNKNOWN
Keywords: bitbucket clone repo link
Platform: UNKNOWN
Classifier: Programming Language :: Python
Classifier: License :: OSI Approved :: MIT License
Classifier: Development Status :: 4 - Beta
Classifier: Operating System :: OS Independent
Classifier: Topic :: System :: Software Distribution
Requires-Dist: requests
Requires-Dist: argparse
Requires-Dist: future
